{"symbols":{"AppRoutingModule":{"hasNamespace":false,"type":0,"moduleName":"app-routing.module","relativePath":"practicebaba\\src\\app\\app-routing.module"},"CounterComponent":{"hasNamespace":false,"type":0,"moduleName":"counter.component","relativePath":"practicebaba\\src\\app\\pages\\counter\\counter.component"},"InputComponent":{"hasNamespace":false,"type":0,"moduleName":"input.component","relativePath":"practicebaba\\src\\app\\pages\\input\\input.component"},"TempInputComponent":{"hasNamespace":false,"type":0,"moduleName":"temp-input.component","relativePath":"practicebaba\\src\\app\\pages\\temp-input\\temp-input.component"},"AppModule":{"hasNamespace":false,"type":0,"moduleName":"app.module","relativePath":"practicebaba\\src\\app\\app.module"},"AppComponent":{"hasNamespace":false,"type":0,"moduleName":"app.component","relativePath":"practicebaba\\src\\app\\app.component"},"ListComponent":{"hasNamespace":false,"type":0,"moduleName":"list.component","relativePath":"practicebaba\\src\\app\\pages\\list\\list.component"},"WrapperComponent":{"hasNamespace":false,"type":0,"moduleName":"wrapper.component","relativePath":"practicebaba\\src\\app\\pages\\wrapper\\wrapper.component"}},"files":{"practicebaba\\src\\app\\app.module.ts":"2023-02-24T03:40:17.569Z","practicebaba\\src\\app\\pages\\input\\input.component.ts":"2023-02-23T13:18:57.510Z","practicebaba\\src\\app\\app.component.ts":"2023-02-24T04:13:15.317Z","practicebaba\\src\\main.ts":"2023-02-23T06:51:54.294Z","practicebaba\\src\\app\\pages\\input\\input.component.spec.ts":"2023-02-23T07:20:21.514Z","practicebaba\\src\\app\\app.component.spec.ts":"2023-02-23T06:51:54.326Z","practicebaba\\src\\app\\app-routing.module.ts":"2023-02-23T06:51:54.317Z","practicebaba\\src\\app\\pages\\counter\\counter.component.ts":"2023-02-23T12:50:02.671Z","practicebaba\\src\\app\\pages\\temp-input\\temp-input.component.ts":"2023-02-23T13:55:40.726Z","practicebaba\\src\\app\\pages\\wrapper\\wrapper.component.ts":"2023-02-24T04:39:38.606Z","practicebaba\\src\\app\\pages\\list\\list.component.ts":"2023-02-24T04:29:01.658Z"}}